Metadata-Version: 2.1
Name: PyGuitar
Version: 0.3.7
Summary: PyGuitar generates an easy-to-practice chord book.
Home-page: UNKNOWN
Author: Shuto Iwasaki
Author-email: cabernet.rock@gmail.com
License: MIT
Project-URL: Source Code, https://github.com/iwasakishuto/PyGuitar
Platform: UNKNOWN
Classifier: Development Status :: 3 - Alpha
Classifier: Intended Audience :: Other Audience
Classifier: License :: OSI Approved :: MIT License
Classifier: Programming Language :: Python :: 3
Classifier: Programming Language :: Python :: 3.6
Classifier: Topic :: Software Development :: Libraries
Classifier: Topic :: Software Development :: Libraries :: Python Modules
Requires-Python: >=3.6
Provides-Extra: tests
